ewatercycle_hype/__init__.py
ewatercycle_hype/forcing.py
ewatercycle_hype/model.py
ewatercycle_hype-0.0.1.dist-info/METADATA
ewatercycle_hype-0.0.1.dist-info/WHEEL
ewatercycle_hype-0.0.1.dist-info/entry_points.txt
ewatercycle_hype-0.0.1.dist-info/licenses/LICENSE.txt
ewatercycle_hype-0.0.1.dist-info/RECORD
