Metadata-Version: 2.1
Name: ewatercycle-hype
Version: 0.0.1
Summary: eWaterCycle plugin for HYPE hydrological model
Author-email: "Bart Schilperoort, Peter Kalverla, Stefan Verhoeven" <b.schilperoort@esciencecenter.nl>
License-Expression: Apache-2.0
License-File: LICENSE.txt
Keywords: ewatercycle,hydrology
Classifier: Intended Audience :: Developers
Classifier: License :: OSI Approved :: Apache Software License
Classifier: Natural Language :: English
Classifier: Operating System :: OS Independent
Classifier: Programming Language :: Python
Classifier: Programming Language :: Python :: 3 :: Only
Requires-Dist: ewatercycle>=2.0.0b2
